soar/__init__.py
soar/cli.py
soar/encryptor.py
soar/fingerprint.py
soar/loader.py
soar/utils.py
soar/walker.py
soar_locker-1.0.dist-info/licenses/LICENSE
soar_locker-1.0.dist-info/METADATA
soar_locker-1.0.dist-info/WHEEL
soar_locker-1.0.dist-info/entry_points.txt
soar_locker-1.0.dist-info/top_level.txt
soar_locker-1.0.dist-info/RECORD
