Metadata-Version: 2.4
Name: soar_locker
Version: 1.0
Summary: SOAR - Secure Obfuscated Archive Runtime (SOAR-Locker)
Author-email: "HuaiYu-Yang@dawlaishi122" <1710802268@qq.com>
License: MIT
Keywords: python encryption,secure python,code protection,machine binding,module encryption,python obfuscation,anti-tamper,aes encrypted python,python protect
Classifier: Programming Language :: Python :: 3
Classifier: Programming Language :: Python :: 3 :: Only
Classifier: Programming Language :: Python :: 3.7
Classifier: License :: OSI Approved :: MIT License
Classifier: Operating System :: OS Independent
Classifier: Topic :: Security
Classifier: Topic :: Software Development :: Libraries
Classifier: Topic :: System :: Archiving
Requires-Python: >=3.7
License-File: LICENSE
Requires-Dist: cryptography>=41.0.0
Requires-Dist: soar_core==1.0.0
Dynamic: license-file
